cloudbrain_modules/README.md
cloudbrain_modules/__init__.py
cloudbrain_modules/ai_blog/__init__.py
cloudbrain_modules/ai_blog/ai_blog_client.py
cloudbrain_modules/ai_blog/blog_api.py
cloudbrain_modules/ai_blog/init_blog_db.py
cloudbrain_modules/ai_blog/test_ai_blog_client.py
cloudbrain_modules/ai_blog/test_blog_api.py
cloudbrain_modules/ai_familio/__init__.py
cloudbrain_modules/ai_familio/familio_api.py
cloudbrain_modules/ai_familio/init_familio_db.py
cloudbrain_modules/bug_tracker/__init__.py
cloudbrain_modules-1.0.5.dist-info/METADATA
cloudbrain_modules-1.0.5.dist-info/WHEEL
cloudbrain_modules-1.0.5.dist-info/top_level.txt
cloudbrain_modules-1.0.5.dist-info/RECORD
