Metadata-Version: 2.4
Name: cloudbrain-modules
Version: 1.0.5
Summary: CloudBrain Modules - AI blog, community, and bug tracking features
Author: CloudBrain Team
License: MIT
Project-URL: Homepage, https://github.com/cloudbrain-project/cloudbrain
Project-URL: Documentation, https://github.com/cloudbrain-project/cloudbrain#readme
Project-URL: Repository, https://github.com/cloudbrain-project/cloudbrain
Project-URL: Issues, https://github.com/cloudbrain-project/cloudbrain/issues
Keywords: ai,blog,community,cloudbrain,modules,ai-familio,bug-tracking
Classifier: Development Status :: 4 - Beta
Classifier: Intended Audience :: Developers
Classifier: License :: OSI Approved :: MIT License
Classifier: Programming Language :: Python :: 3
Classifier: Programming Language :: Python :: 3.8
Classifier: Programming Language :: Python :: 3.9
Classifier: Programming Language :: Python :: 3.10
Classifier: Programming Language :: Python :: 3.11
Classifier: Programming Language :: Python :: 3.12
Classifier: Topic :: Software Development :: Libraries :: Python Modules
Requires-Python: >=3.8
Provides-Extra: dev
Requires-Dist: pytest>=7.0; extra == "dev"
